norma43parser/__init__.py
norma43parser/models/__init__.py
norma43parser/models/account.py
norma43parser/models/footer.py
norma43parser/models/header.py
norma43parser/models/movement_line.py
norma43parser/models/norma_43_document.py
norma43parser/parsers/__init__.py
norma43parser/parsers/date_format.py
norma43parser/parsers/end_of_file_parser.py
norma43parser/parsers/footer_parser.py
norma43parser/parsers/header_parser.py
norma43parser/parsers/line_parser.py
norma43parser/parsers/line_parser_factory.py
norma43parser/parsers/line_type.py
norma43parser/parsers/movement_line_extra_information_parser.py
norma43parser/parsers/movement_line_parser.py
norma43parser/parsers/norma_43_parser.py
norma43parser-1.1.2.dist-info/LICENSE.txt
norma43parser-1.1.2.dist-info/METADATA
norma43parser-1.1.2.dist-info/WHEEL
norma43parser-1.1.2.dist-info/top_level.txt
norma43parser-1.1.2.dist-info/RECORD
