Metadata-Version: 2.1
Name: norma43parser
Version: 1.1.2
Summary: Parser for Bank Account information files formatted in Norma 43
Home-page: https://github.com/sergief/norma43parser
Author: Sergi Espinar
Author-email: sergief@users.noreply.github.com
License: MIT
Keywords: norma43,parser,bank,account,n43,csb
Platform: UNKNOWN
Classifier: Development Status :: 4 - Beta
Classifier: Intended Audience :: Developers
Classifier: Topic :: Software Development :: Libraries :: Python Modules
Classifier: License :: OSI Approved :: MIT License
Classifier: Programming Language :: Python :: 3.6
Classifier: Programming Language :: Python :: 3.7
Classifier: Programming Language :: Python :: 3.8
Requires-Python: >=3.6
